logiccircuit/__init__.py
logiccircuit/__main__.py
logiccircuit/classes.py
logiccircuit/colors.py
logiccircuit/logic.py
logiccircuit/logiccircuit.py
logiccircuit/logo.png
logiccircuit/py.typed
LogicCircuit-1.0.1.dist-info/LICENSE
LogicCircuit-1.0.1.dist-info/METADATA
LogicCircuit-1.0.1.dist-info/WHEEL
LogicCircuit-1.0.1.dist-info/top_level.txt
LogicCircuit-1.0.1.dist-info/RECORD
