Metadata-Version: 2.1
Name: LogicCircuit
Version: 1.0.1
Summary: Simple circuit builder only using logic gates
Home-page: https://github.com/TINYT1ME/LogicCircuit
Author: TINYT1ME
License: MIT
Platform: UNKNOWN
Classifier: Programming Language :: Python :: 3
Classifier: Programming Language :: Python :: 3 :: Only
Classifier: Programming Language :: Python :: 3.6
Classifier: Programming Language :: Python :: 3.7
Classifier: Programming Language :: Python :: 3.8
Classifier: Programming Language :: Python :: 3.9
Classifier: Programming Language :: Python :: 3.10
Classifier: Topic :: Software Development :: Libraries :: pygame
Classifier: Development Status :: 2 - Pre-Alpha
Requires-Python: >=3.6
License-File: LICENSE
Requires-Dist: pygame (>=2.1)
Provides-Extra: testing
Requires-Dist: black (==21.12b0) ; extra == 'testing'
Requires-Dist: mypy (==0.931) ; extra == 'testing'
